rximg/__init__.py
rximg/app.py
rximg/demo.py
rximg/setup.py
rximg/configs/canny.json
rximg/configs/clspaddlehub.json
rximg/configs/highpass.json
rximg/configs/matchtemplate.json
rximg/configs/of.json
rximg/configs/seamlessclone.json
rximg/configs/sobel.json
rximg/configs/test.json
rximg/configs/test2.json
rximg/custom/__init__.py
rximg/custom/core.py
rximg/custom/custom.py
rximg/custom/cvdl.py
rximg/custom/pdhub.py
rximg/data/Lenna.png
rximg/data/RxImg.png
rximg/data/detect.jpg
rximg/data/target.jpg
rximg/data/text0.jpg
rximg/data/text1.jpg
rximg/data/textcarrc.jpg
rximg/data/wd.jpg
rximg/engine/__init__.py
rximg/engine/dag.py
rximg/engine/decorators.py
rximg/engine/func_factory.py
rximg/engine/get_all_modules.py
rximg/engine/load.py
rximg/engine/module_parsers.py
rximg/engine/ndarray_tools.py
rximg/frontend/dist/favicon.ico
rximg/frontend/dist/index.html
rximg/frontend/dist/assets/favicon.bac6fa58.ico
rximg/frontend/dist/assets/index.0a269c62.js
rximg/frontend/dist/assets/index.33d099d2.css
rximg/frontend/dist/assets/index.638910f3.js
rximg/frontend/dist/assets/index.703704e0.css
rximg/frontend/dist/assets/index.9ab8dd09.css
rximg/frontend/dist/assets/index.a49cfcdb.js
rximg/third_party/__init__.py
rximg/third_party/cv2_enums.py
rximg/third_party/cv2_modules.py
rximg/third_party/filemanager.py
rximg/third_party/np_enums.py
rximg/third_party/np_modules.py
rximg/third_party/observer_modules.py
rximg/third_party/rxtypes.py
rximg/utils/__init__.py
rximg/utils/config.py
rximg/utils/exception.py
rximg-0.1.4.dist-info/METADATA
rximg-0.1.4.dist-info/WHEEL
rximg-0.1.4.dist-info/top_level.txt
rximg-0.1.4.dist-info/RECORD
