Metadata-Version: 2.1
Name: rximg
Version: 0.1.4
Summary: rximg package
Author: rximg
License: MIT License
Classifier: Programming Language :: Python :: 3
Classifier: Programming Language :: Python :: 3.9
Requires-Python: >=3.9
Requires-Dist: Flask
Requires-Dist: Flask-Cors
Requires-Dist: Flask-SocketIO
Requires-Dist: numpy
Requires-Dist: requests
Requires-Dist: opencv-python
Requires-Dist: reactivex
